{"playerID":78789,"firstName":"Gabin","lastName":"Bernardeau","shortName":"G. Bernardeau","fullName":"Gabin Bernardeau","homeName":"","country":{"name":"France","id":74},"currentTeam":{"name":null,"id":0},"photo":"","additionalInfo":{"height":"181 cm","weight":"75 kg","position":3,"Fantasy Value":null,"birthdate":"24-01-2006  (20)"},"teams":[],"stat":[{"season_name":"FRANCE: Coupe de France 2025-26","season_id":603,"team_name":"OGC Nice","played":2,"career_lineup":1,"career_minutes":98,"career_subsin":1,"career_subsout":0,"1 Point (basketball)":0,"2 Points (basketball)":0,"3 Points (basketball)":0,"Points (basketball)":0,"Goals":0,"Assist":0,"Yellow card":0,"Second yellow":0,"Red card":0,"Own goal":0,"Penalty goal":0,"Missed penalty":0,"Goal":0,"Penalty shootout scored":0,"Penalty shootout missed":1},{"season_name":"UEFA Europa League 2025-26","season_id":592,"team_name":"OGC Nice","played":0,"career_lineup":0,"career_minutes":0,"career_subsin":0,"career_subsout":0,"1 Point (basketball)":0,"2 Points (basketball)":0,"3 Points (basketball)":0,"Points (basketball)":0,"Goals":0,"Assist":0,"Yellow card":0,"Second yellow":0,"Red card":0,"Own goal":0,"Penalty goal":0,"Missed penalty":0,"Goal":0,"Penalty shootout scored":0,"Penalty shootout missed":0},{"season_name":"FRANCE: Ligue 1 2025-26","season_id":519,"team_name":"OGC Nice","played":4,"career_lineup":1,"career_minutes":93,"career_subsin":3,"career_subsout":1,"1 Point (basketball)":0,"2 Points (basketball)":0,"3 Points (basketball)":0,"Points (basketball)":0,"Goals":0,"Assist":0,"Yellow card":0,"Second yellow":0,"Red card":0,"Own goal":0,"Penalty goal":0,"Missed penalty":0,"Goal":0,"Penalty shootout scored":0,"Penalty shootout missed":0},{"season_name":"FRANCE: Coupe de France 2024-25","season_id":441,"team_name":"Le Mans FC","played":2,"career_lineup":2,"career_minutes":132,"career_subsin":0,"career_subsout":2,"1 Point (basketball)":0,"2 Points (basketball)":0,"3 Points (basketball)":0,"Points (basketball)":0,"Goals":0,"Assist":0,"Yellow card":1,"Second yellow":0,"Red card":0,"Own goal":0,"Penalty goal":0,"Missed penalty":0,"Goal":0,"Penalty shootout scored":0,"Penalty shootout missed":0}],"matches":[{"matchID":145207,"matchDate":"2026-03-04","matchTime":"19:30","minutes_played":8,"lineUP":"0","homeParticipant":{"participantID":545,"score":0,"participantName":"FC Lorient","teamShortName":"FCL","teamMiddleName":"Lorient","logo":"https://api.statorium.com/media/bearleague/bl1716376354282.webp"},"awayParticipant":{"participantID":64,"score":0,"participantName":"OGC Nice","teamShortName":"NCE","teamMiddleName":"Nice","logo":"https://api.statorium.com/media/bearleague/bl171637666030.webp"},"playerEvents":[{"eventID":20,"eventName":"Penalty shootout missed","minutes":""}]},{"matchID":124237,"matchDate":"2026-03-01","matchTime":"14:00","minutes_played":23,"lineUP":"0","homeParticipant":{"participantID":628,"score":1,"participantName":"Paris FC","teamShortName":"PAR","teamMiddleName":"Paris","logo":"https://api.statorium.com/media/bearleague/bl15979293751734.webp"},"awayParticipant":{"participantID":64,"score":0,"participantName":"OGC Nice","teamShortName":"NCE","teamMiddleName":"Nice","logo":"https://api.statorium.com/media/bearleague/bl171637666030.webp"},"playerEvents":[]},{"matchID":124227,"matchDate":"2026-02-22","matchTime":"16:15","minutes_played":5,"lineUP":"0","homeParticipant":{"participantID":64,"score":3,"participantName":"OGC Nice","teamShortName":"NCE","teamMiddleName":"Nice","logo":"https://api.statorium.com/media/bearleague/bl171637666030.webp"},"awayParticipant":{"participantID":545,"score":3,"participantName":"FC Lorient","teamShortName":"FCL","teamMiddleName":"Lorient","logo":"https://api.statorium.com/media/bearleague/bl1716376354282.webp"},"playerEvents":[]},{"matchID":124211,"matchDate":"2026-02-08","matchTime":"14:00","minutes_played":64,"lineUP":"1","homeParticipant":{"participantID":64,"score":0,"participantName":"OGC Nice","teamShortName":"NCE","teamMiddleName":"Nice","logo":"https://api.statorium.com/media/bearleague/bl171637666030.webp"},"awayParticipant":{"participantID":76,"score":0,"participantName":"AS Monaco","teamShortName":"ASM","teamMiddleName":"Monaco","logo":"https://api.statorium.com/media/bearleague/bl17163762842259.webp"},"playerEvents":[]},{"matchID":141704,"matchDate":"2026-02-04","matchTime":"19:30","minutes_played":"90","lineUP":"1","homeParticipant":{"participantID":64,"score":3,"participantName":"OGC Nice","teamShortName":"NCE","teamMiddleName":"Nice","logo":"https://api.statorium.com/media/bearleague/bl171637666030.webp"},"awayParticipant":{"participantID":65,"score":2,"participantName":"HSC Montpellier","teamShortName":"MPL","teamMiddleName":"Montpellier","logo":"https://api.statorium.com/media/bearleague/bl17163767271425.webp"},"playerEvents":[]},{"matchID":124192,"matchDate":"2026-01-25","matchTime":"14:00","minutes_played":1,"lineUP":"0","homeParticipant":{"participantID":60,"score":1,"participantName":"FC Nantes","teamShortName":"NAN","teamMiddleName":"Nantes","logo":"https://api.statorium.com/media/bearleague/bl1716376414855.webp"},"awayParticipant":{"participantID":64,"score":4,"participantName":"OGC Nice","teamShortName":"NCE","teamMiddleName":"Nice","logo":"https://api.statorium.com/media/bearleague/bl171637666030.webp"},"playerEvents":[]},{"matchID":110189,"matchDate":"2025-02-04","matchTime":"20:10","minutes_played":64,"lineUP":"1","homeParticipant":{"participantID":1575,"score":0,"participantName":"Le Mans FC","teamShortName":"MAN","teamMiddleName":"Le Mans","logo":"https://api.statorium.com/media/bearleague/bl1666978845572.webp"},"awayParticipant":{"participantID":66,"score":2,"participantName":"Paris Saint-Germain","teamShortName":"PSG","teamMiddleName":"PSG","logo":"https://api.statorium.com/media/bearleague/bl17163765602938.webp"},"playerEvents":[{"eventID":5,"eventName":"Yellow card","minutes":"5"}]},{"matchID":107865,"matchDate":"2025-01-14","matchTime":"19:45","minutes_played":68,"lineUP":"1","homeParticipant":{"participantID":1575,"score":1,"participantName":"Le Mans FC","teamShortName":"MAN","teamMiddleName":"Le Mans","logo":"https://api.statorium.com/media/bearleague/bl1666978845572.webp"},"awayParticipant":{"participantID":633,"score":1,"participantName":"Valenciennes FC","teamShortName":"VAL","teamMiddleName":"Valenciennes","logo":"https://api.statorium.com/media/bearleague/bl1597929801745.webp"},"playerEvents":[]}]}