{"playerID":77447,"firstName":"Mirza","lastName":"Catovic","shortName":"M. Catovic","fullName":"Mirza Catovic","homeName":"Мирза Ћатовић","country":{"name":null,"id":0},"currentTeam":{"name":null,"id":0},"photo":"","additionalInfo":{"height":"187 cm","weight":"83 kg","position":3,"Fantasy Value":null,"birthdate":"01-05-2007  (18)"},"teams":[],"stat":[{"season_name":"GERMANY: DFB-Pokal 2025-26","season_id":557,"team_name":"VfB Stuttgart","played":0,"career_lineup":0,"career_minutes":0,"career_subsin":0,"career_subsout":0,"1 Point (basketball)":0,"2 Points (basketball)":0,"3 Points (basketball)":0,"Points (basketball)":0,"Goals":0,"Assist":0,"Yellow card":0,"Second yellow":0,"Red card":0,"Own goal":0,"Penalty goal":0,"Missed penalty":0,"Goal":0,"Penalty shootout scored":0,"Penalty shootout missed":0},{"season_name":"UEFA Europa League 2025-26","season_id":592,"team_name":"VfB Stuttgart","played":0,"career_lineup":0,"career_minutes":0,"career_subsin":0,"career_subsout":0,"1 Point (basketball)":0,"2 Points (basketball)":0,"3 Points (basketball)":0,"Points (basketball)":0,"Goals":0,"Assist":0,"Yellow card":0,"Second yellow":0,"Red card":0,"Own goal":0,"Penalty goal":0,"Missed penalty":0,"Goal":0,"Penalty shootout scored":0,"Penalty shootout missed":0},{"season_name":"GERMANY: Bundesliga 2025-26","season_id":521,"team_name":"VfB Stuttgart","played":0,"career_lineup":0,"career_minutes":0,"career_subsin":0,"career_subsout":0,"1 Point (basketball)":0,"2 Points (basketball)":0,"3 Points (basketball)":0,"Points (basketball)":0,"Goals":0,"Assist":0,"Yellow card":0,"Second yellow":0,"Red card":0,"Own goal":0,"Penalty goal":0,"Missed penalty":0,"Goal":0,"Penalty shootout scored":0,"Penalty shootout missed":0},{"season_name":"GERMANY: 3. Liga 2025-26","season_id":523,"team_name":"VfB Stuttgart II","played":26,"career_lineup":25,"career_minutes":2071,"career_subsin":1,"career_subsout":6,"1 Point (basketball)":0,"2 Points (basketball)":0,"3 Points (basketball)":0,"Points (basketball)":0,"Goals":1,"Assist":0,"Yellow card":8,"Second yellow":0,"Red card":0,"Own goal":0,"Penalty goal":0,"Missed penalty":0,"Goal":1,"Penalty shootout scored":0,"Penalty shootout missed":0},{"season_name":"GERMANY: 3. Liga 2024-25","season_id":392,"team_name":"VfB Stuttgart II","played":14,"career_lineup":7,"career_minutes":726,"career_subsin":7,"career_subsout":4,"1 Point (basketball)":0,"2 Points (basketball)":0,"3 Points (basketball)":0,"Points (basketball)":0,"Goals":1,"Assist":0,"Yellow card":3,"Second yellow":0,"Red card":0,"Own goal":0,"Penalty goal":0,"Missed penalty":0,"Goal":1,"Penalty shootout scored":0,"Penalty shootout missed":0}],"matches":[{"matchID":129420,"matchDate":"2026-04-26","matchTime":"17:30","minutes_played":"90","lineUP":"1","homeParticipant":{"participantID":3752,"score":3,"participantName":"TSV Havelse","teamShortName":"HAV","teamMiddleName":"Havelse","logo":"https://api.statorium.com/media/bearleague/bl17518890252414.webp"},"awayParticipant":{"participantID":2806,"score":2,"participantName":"VfB Stuttgart II","teamShortName":"STU II","teamMiddleName":"Stuttgart II","logo":"https://api.statorium.com/media/bearleague/bl17207470461799.webp"},"playerEvents":[{"eventID":5,"eventName":"Yellow card","minutes":"40"}]},{"matchID":129379,"matchDate":"2026-04-04","matchTime":"14:30","minutes_played":48,"lineUP":"1","homeParticipant":{"participantID":2806,"score":3,"participantName":"VfB Stuttgart II","teamShortName":"STU II","teamMiddleName":"Stuttgart II","logo":"https://api.statorium.com/media/bearleague/bl17207470461799.webp"},"awayParticipant":{"participantID":913,"score":1,"participantName":"SSV Jahn Regensburg","teamShortName":"JAH","teamMiddleName":"Regensburg","logo":"https://api.statorium.com/media/bearleague/bl16154605162168.webp"},"playerEvents":[]},{"matchID":129369,"matchDate":"2026-03-21","matchTime":"13:00","minutes_played":"90","lineUP":"1","homeParticipant":{"participantID":3731,"score":3,"participantName":"1. FC Schweinfurt 05","teamShortName":"S05","teamMiddleName":"Schweinfurt 05","logo":"https://api.statorium.com/media/bearleague/bl1751479129154.webp"},"awayParticipant":{"participantID":2806,"score":1,"participantName":"VfB Stuttgart II","teamShortName":"STU II","teamMiddleName":"Stuttgart II","logo":"https://api.statorium.com/media/bearleague/bl17207470461799.webp"},"playerEvents":[]},{"matchID":129358,"matchDate":"2026-03-15","matchTime":"12:30","minutes_played":"90","lineUP":"1","homeParticipant":{"participantID":2806,"score":1,"participantName":"VfB Stuttgart II","teamShortName":"STU II","teamMiddleName":"Stuttgart II","logo":"https://api.statorium.com/media/bearleague/bl17207470461799.webp"},"awayParticipant":{"participantID":3753,"score":0,"participantName":"TSG 1899 Hoffenheim II","teamShortName":"TSG","teamMiddleName":"Hoffenheim II","logo":"https://api.statorium.com/media/bearleague/bl17518891642577.webp"},"playerEvents":[]},{"matchID":129352,"matchDate":"2026-03-07","matchTime":"13:00","minutes_played":46,"lineUP":"1","homeParticipant":{"participantID":1180,"score":2,"participantName":"SV Wehen Wiesbaden","teamShortName":"SV","teamMiddleName":"Wehen","logo":"https://api.statorium.com/media/bearleague/bl16425082741208.webp"},"awayParticipant":{"participantID":2806,"score":1,"participantName":"VfB Stuttgart II","teamShortName":"STU II","teamMiddleName":"Stuttgart II","logo":"https://api.statorium.com/media/bearleague/bl17207470461799.webp"},"playerEvents":[]},{"matchID":129338,"matchDate":"2026-03-03","matchTime":"18:00","minutes_played":"90","lineUP":"1","homeParticipant":{"participantID":2806,"score":1,"participantName":"VfB Stuttgart II","teamShortName":"STU II","teamMiddleName":"Stuttgart II","logo":"https://api.statorium.com/media/bearleague/bl17207470461799.webp"},"awayParticipant":{"participantID":1334,"score":2,"participantName":"FC Energie Cottbus","teamShortName":"ENE","teamMiddleName":"Energie Cottbus","logo":"https://api.statorium.com/media/bearleague/bl16574919151246.webp"},"playerEvents":[]},{"matchID":129331,"matchDate":"2026-02-28","matchTime":"13:00","minutes_played":"90","lineUP":"1","homeParticipant":{"participantID":1192,"score":2,"participantName":"FC Viktoria Köln","teamShortName":"VIK","teamMiddleName":"Viktoria Köln","logo":"https://api.statorium.com/media/bearleague/bl16425104911996.webp"},"awayParticipant":{"participantID":2806,"score":0,"participantName":"VfB Stuttgart II","teamShortName":"STU II","teamMiddleName":"Stuttgart II","logo":"https://api.statorium.com/media/bearleague/bl17207470461799.webp"},"playerEvents":[]},{"matchID":129306,"matchDate":"2026-02-14","matchTime":"13:00","minutes_played":"90","lineUP":"1","homeParticipant":{"participantID":1289,"score":2,"participantName":"1. FC Saarbrücken","teamShortName":"FCS","teamMiddleName":"Saarbrücken","logo":"https://api.statorium.com/media/bearleague/bl16558179732987.webp"},"awayParticipant":{"participantID":2806,"score":0,"participantName":"VfB Stuttgart II","teamShortName":"STU II","teamMiddleName":"Stuttgart II","logo":"https://api.statorium.com/media/bearleague/bl17207470461799.webp"},"playerEvents":[]},{"matchID":129300,"matchDate":"2026-02-07","matchTime":"15:30","minutes_played":"90","lineUP":"1","homeParticipant":{"participantID":2806,"score":2,"participantName":"VfB Stuttgart II","teamShortName":"STU II","teamMiddleName":"Stuttgart II","logo":"https://api.statorium.com/media/bearleague/bl17207470461799.webp"},"awayParticipant":{"participantID":1179,"score":1,"participantName":"TSV 1860 München","teamShortName":"M60","teamMiddleName":"1860 Munich","logo":"https://api.statorium.com/media/bearleague/bl16425698392544.webp"},"playerEvents":[]},{"matchID":129291,"matchDate":"2026-02-01","matchTime":"15:30","minutes_played":"90","lineUP":"1","homeParticipant":{"participantID":1288,"score":4,"participantName":"SC Verl","teamShortName":"SCV","teamMiddleName":"Verl","logo":"https://api.statorium.com/media/bearleague/bl16558182132782.webp"},"awayParticipant":{"participantID":2806,"score":0,"participantName":"VfB Stuttgart II","teamShortName":"STU II","teamMiddleName":"Stuttgart II","logo":"https://api.statorium.com/media/bearleague/bl17207470461799.webp"},"playerEvents":[{"eventID":5,"eventName":"Yellow card","minutes":"67"}]},{"matchID":129277,"matchDate":"2026-01-24","matchTime":"13:00","minutes_played":"90","lineUP":"1","homeParticipant":{"participantID":974,"score":2,"participantName":"FC Ingolstadt 04","teamShortName":"FCI","teamMiddleName":"Ingolstadt","logo":"https://api.statorium.com/media/bearleague/bl16251447601419.webp"},"awayParticipant":{"participantID":2806,"score":1,"participantName":"VfB Stuttgart II","teamShortName":"STU II","teamMiddleName":"Stuttgart II","logo":"https://api.statorium.com/media/bearleague/bl17207470461799.webp"},"playerEvents":[]},{"matchID":129269,"matchDate":"2026-01-18","matchTime":"12:30","minutes_played":"90","lineUP":"1","homeParticipant":{"participantID":2806,"score":0,"participantName":"VfB Stuttgart II","teamShortName":"STU II","teamMiddleName":"Stuttgart II","logo":"https://api.statorium.com/media/bearleague/bl17207470461799.webp"},"awayParticipant":{"participantID":1284,"score":4,"participantName":"MSV Duisburg","teamShortName":"DUI","teamMiddleName":"Duisburg","logo":"https://api.statorium.com/media/bearleague/bl16896376061292.webp"},"playerEvents":[]},{"matchID":129261,"matchDate":"2025-12-20","matchTime":"13:00","minutes_played":46,"lineUP":"1","homeParticipant":{"participantID":915,"score":1,"participantName":"VfL Osnabrück","teamShortName":"OSN","teamMiddleName":"Osnabrück","logo":"https://api.statorium.com/media/bearleague/bl16886921952722.webp"},"awayParticipant":{"participantID":2806,"score":2,"participantName":"VfB Stuttgart II","teamShortName":"STU II","teamMiddleName":"Stuttgart II","logo":"https://api.statorium.com/media/bearleague/bl17207470461799.webp"},"playerEvents":[]},{"matchID":129229,"matchDate":"2025-11-30","matchTime":"18:30","minutes_played":"90","lineUP":"1","homeParticipant":{"participantID":2806,"score":2,"participantName":"VfB Stuttgart II","teamShortName":"STU II","teamMiddleName":"Stuttgart II","logo":"https://api.statorium.com/media/bearleague/bl17207470461799.webp"},"awayParticipant":{"participantID":3752,"score":1,"participantName":"TSV Havelse","teamShortName":"HAV","teamMiddleName":"Havelse","logo":"https://api.statorium.com/media/bearleague/bl17518890252414.webp"},"playerEvents":[]},{"matchID":129214,"matchDate":"2025-11-23","matchTime":"15:30","minutes_played":75,"lineUP":"1","homeParticipant":{"participantID":911,"score":0,"participantName":"FC Erzgebirge Aue","teamShortName":"ERZ","teamMiddleName":"Erzgebirge Aue","logo":"https://api.statorium.com/media/bearleague/bl17207463292647.webp"},"awayParticipant":{"participantID":2806,"score":0,"participantName":"VfB Stuttgart II","teamShortName":"STU II","teamMiddleName":"Stuttgart II","logo":"https://api.statorium.com/media/bearleague/bl17207470461799.webp"},"playerEvents":[{"eventID":5,"eventName":"Yellow card","minutes":"61"}]},{"matchID":129200,"matchDate":"2025-11-01","matchTime":"13:00","minutes_played":"90","lineUP":"1","homeParticipant":{"participantID":1203,"score":2,"participantName":"SSV Ulm 1846","teamShortName":"ULM","teamMiddleName":"SSV Ulm","logo":"https://api.statorium.com/media/bearleague/bl16425127271498.webp"},"awayParticipant":{"participantID":2806,"score":2,"participantName":"VfB Stuttgart II","teamShortName":"STU II","teamMiddleName":"Stuttgart II","logo":"https://api.statorium.com/media/bearleague/bl17207470461799.webp"},"playerEvents":[{"eventID":5,"eventName":"Yellow card","minutes":"90+1"}]},{"matchID":129188,"matchDate":"2025-10-25","matchTime":"12:00","minutes_played":8,"lineUP":"0","homeParticipant":{"participantID":913,"score":3,"participantName":"SSV Jahn Regensburg","teamShortName":"JAH","teamMiddleName":"Regensburg","logo":"https://api.statorium.com/media/bearleague/bl16154605162168.webp"},"awayParticipant":{"participantID":2806,"score":2,"participantName":"VfB Stuttgart II","teamShortName":"STU II","teamMiddleName":"Stuttgart II","logo":"https://api.statorium.com/media/bearleague/bl17207470461799.webp"},"playerEvents":[]},{"matchID":129166,"matchDate":"2025-10-05","matchTime":"17:30","minutes_played":73,"lineUP":"1","homeParticipant":{"participantID":3753,"score":1,"participantName":"TSG 1899 Hoffenheim II","teamShortName":"TSG","teamMiddleName":"Hoffenheim II","logo":"https://api.statorium.com/media/bearleague/bl17518891642577.webp"},"awayParticipant":{"participantID":2806,"score":3,"participantName":"VfB Stuttgart II","teamShortName":"STU II","teamMiddleName":"Stuttgart II","logo":"https://api.statorium.com/media/bearleague/bl17207470461799.webp"},"playerEvents":[]},{"matchID":129158,"matchDate":"2025-09-30","matchTime":"17:00","minutes_played":"90","lineUP":"1","homeParticipant":{"participantID":2806,"score":0,"participantName":"VfB Stuttgart II","teamShortName":"STU II","teamMiddleName":"Stuttgart II","logo":"https://api.statorium.com/media/bearleague/bl17207470461799.webp"},"awayParticipant":{"participantID":1180,"score":0,"participantName":"SV Wehen Wiesbaden","teamShortName":"SV","teamMiddleName":"Wehen","logo":"https://api.statorium.com/media/bearleague/bl16425082741208.webp"},"playerEvents":[{"eventID":5,"eventName":"Yellow card","minutes":"72"}]},{"matchID":129138,"matchDate":"2025-09-20","matchTime":"12:00","minutes_played":"90","lineUP":"1","homeParticipant":{"participantID":2806,"score":2,"participantName":"VfB Stuttgart II","teamShortName":"STU II","teamMiddleName":"Stuttgart II","logo":"https://api.statorium.com/media/bearleague/bl17207470461799.webp"},"awayParticipant":{"participantID":1192,"score":1,"participantName":"FC Viktoria Köln","teamShortName":"VIK","teamMiddleName":"Viktoria Köln","logo":"https://api.statorium.com/media/bearleague/bl16425104911996.webp"},"playerEvents":[{"eventID":5,"eventName":"Yellow card","minutes":"72"}]},{"matchID":129126,"matchDate":"2025-09-17","matchTime":"17:00","minutes_played":65,"lineUP":"1","homeParticipant":{"participantID":1185,"score":0,"participantName":"SV Waldhof Mannheim","teamShortName":"SVW","teamMiddleName":"Waldhof Mannheim","logo":"https://api.statorium.com/media/bearleague/bl16425086321073.webp"},"awayParticipant":{"participantID":2806,"score":1,"participantName":"VfB Stuttgart II","teamShortName":"STU II","teamMiddleName":"Stuttgart II","logo":"https://api.statorium.com/media/bearleague/bl17207470461799.webp"},"playerEvents":[]},{"matchID":129121,"matchDate":"2025-09-13","matchTime":"12:00","minutes_played":"90","lineUP":"1","homeParticipant":{"participantID":2806,"score":1,"participantName":"VfB Stuttgart II","teamShortName":"STU II","teamMiddleName":"Stuttgart II","logo":"https://api.statorium.com/media/bearleague/bl17207470461799.webp"},"awayParticipant":{"participantID":1289,"score":3,"participantName":"1. FC Saarbrücken","teamShortName":"FCS","teamMiddleName":"Saarbrücken","logo":"https://api.statorium.com/media/bearleague/bl16558179732987.webp"},"playerEvents":[]},{"matchID":129105,"matchDate":"2025-08-30","matchTime":"12:00","minutes_played":"90","lineUP":"1","homeParticipant":{"participantID":1179,"score":1,"participantName":"TSV 1860 München","teamShortName":"M60","teamMiddleName":"1860 Munich","logo":"https://api.statorium.com/media/bearleague/bl16425698392544.webp"},"awayParticipant":{"participantID":2806,"score":1,"participantName":"VfB Stuttgart II","teamShortName":"STU II","teamMiddleName":"Stuttgart II","logo":"https://api.statorium.com/media/bearleague/bl17207470461799.webp"},"playerEvents":[{"eventID":1,"eventName":"Goal","minutes":"25"}]},{"matchID":129100,"matchDate":"2025-08-23","matchTime":"12:00","minutes_played":"90","lineUP":"1","homeParticipant":{"participantID":2806,"score":1,"participantName":"VfB Stuttgart II","teamShortName":"STU II","teamMiddleName":"Stuttgart II","logo":"https://api.statorium.com/media/bearleague/bl17207470461799.webp"},"awayParticipant":{"participantID":1288,"score":1,"participantName":"SC Verl","teamShortName":"SCV","teamMiddleName":"Verl","logo":"https://api.statorium.com/media/bearleague/bl16558182132782.webp"},"playerEvents":[]},{"matchID":129089,"matchDate":"2025-08-10","matchTime":"17:30","minutes_played":"90","lineUP":"1","homeParticipant":{"participantID":2806,"score":2,"participantName":"VfB Stuttgart II","teamShortName":"STU II","teamMiddleName":"Stuttgart II","logo":"https://api.statorium.com/media/bearleague/bl17207470461799.webp"},"awayParticipant":{"participantID":974,"score":1,"participantName":"FC Ingolstadt 04","teamShortName":"FCI","teamMiddleName":"Ingolstadt","logo":"https://api.statorium.com/media/bearleague/bl16251447601419.webp"},"playerEvents":[{"eventID":5,"eventName":"Yellow card","minutes":"50"}]},{"matchID":129076,"matchDate":"2025-08-02","matchTime":"14:30","minutes_played":"90","lineUP":"1","homeParticipant":{"participantID":1284,"score":2,"participantName":"MSV Duisburg","teamShortName":"DUI","teamMiddleName":"Duisburg","logo":"https://api.statorium.com/media/bearleague/bl16896376061292.webp"},"awayParticipant":{"participantID":2806,"score":1,"participantName":"VfB Stuttgart II","teamShortName":"STU II","teamMiddleName":"Stuttgart II","logo":"https://api.statorium.com/media/bearleague/bl17207470461799.webp"},"playerEvents":[{"eventID":5,"eventName":"Yellow card","minutes":"76"}]},{"matchID":90696,"matchDate":"2025-05-17","matchTime":"11:30","minutes_played":"90","lineUP":"1","homeParticipant":{"participantID":2806,"score":1,"participantName":"VfB Stuttgart II","teamShortName":"STU II","teamMiddleName":"Stuttgart II","logo":"https://api.statorium.com/media/bearleague/bl17207470461799.webp"},"awayParticipant":{"participantID":1285,"score":1,"participantName":"Rot-Weiss Essen","teamShortName":"RWE","teamMiddleName":"Essen","logo":"https://api.statorium.com/media/bearleague/bl16558166382360.webp"},"playerEvents":[]},{"matchID":90681,"matchDate":"2025-05-09","matchTime":"17:00","minutes_played":28,"lineUP":"0","homeParticipant":{"participantID":1283,"score":0,"participantName":"Borussia Dortmund II","teamShortName":"BVB II","teamMiddleName":"Dortmund II","logo":"https://api.statorium.com/media/bearleague/bl17158005282749.webp"},"awayParticipant":{"participantID":2806,"score":1,"participantName":"VfB Stuttgart II","teamShortName":"STU II","teamMiddleName":"Stuttgart II","logo":"https://api.statorium.com/media/bearleague/bl17207470461799.webp"},"playerEvents":[]},{"matchID":90676,"matchDate":"2025-05-03","matchTime":"12:00","minutes_played":44,"lineUP":"0","homeParticipant":{"participantID":2806,"score":2,"participantName":"VfB Stuttgart II","teamShortName":"STU II","teamMiddleName":"Stuttgart II","logo":"https://api.statorium.com/media/bearleague/bl17207470461799.webp"},"awayParticipant":{"participantID":2635,"score":1,"participantName":"Alemannia Aachen","teamShortName":"ALE","teamMiddleName":"Alemannia","logo":"https://api.statorium.com/media/bearleague/bl17194411621081.webp"},"playerEvents":[]},{"matchID":90663,"matchDate":"2025-04-27","matchTime":"17:30","minutes_played":"90","lineUP":"1","homeParticipant":{"participantID":1185,"score":0,"participantName":"SV Waldhof Mannheim","teamShortName":"SVW","teamMiddleName":"Waldhof Mannheim","logo":"https://api.statorium.com/media/bearleague/bl16425086321073.webp"},"awayParticipant":{"participantID":2806,"score":0,"participantName":"VfB Stuttgart II","teamShortName":"STU II","teamMiddleName":"Stuttgart II","logo":"https://api.statorium.com/media/bearleague/bl17207470461799.webp"},"playerEvents":[{"eventID":5,"eventName":"Yellow card","minutes":"62"}]},{"matchID":90656,"matchDate":"2025-04-19","matchTime":"14:30","minutes_played":79,"lineUP":"1","homeParticipant":{"participantID":2806,"score":1,"participantName":"VfB Stuttgart II","teamShortName":"STU II","teamMiddleName":"Stuttgart II","logo":"https://api.statorium.com/media/bearleague/bl17207470461799.webp"},"awayParticipant":{"participantID":1288,"score":1,"participantName":"SC Verl","teamShortName":"SCV","teamMiddleName":"Verl","logo":"https://api.statorium.com/media/bearleague/bl16558182132782.webp"},"playerEvents":[{"eventID":5,"eventName":"Yellow card","minutes":"59"}]},{"matchID":90636,"matchDate":"2025-04-08","matchTime":"17:00","minutes_played":68,"lineUP":"1","homeParticipant":{"participantID":2806,"score":1,"participantName":"VfB Stuttgart II","teamShortName":"STU II","teamMiddleName":"Stuttgart II","logo":"https://api.statorium.com/media/bearleague/bl17207470461799.webp"},"awayParticipant":{"participantID":1192,"score":2,"participantName":"FC Viktoria Köln","teamShortName":"VIK","teamMiddleName":"Viktoria Köln","logo":"https://api.statorium.com/media/bearleague/bl16425104911996.webp"},"playerEvents":[]},{"matchID":90620,"matchDate":"2025-04-05","matchTime":"12:00","minutes_played":29,"lineUP":"0","homeParticipant":{"participantID":911,"score":2,"participantName":"FC Erzgebirge Aue","teamShortName":"ERZ","teamMiddleName":"Erzgebirge Aue","logo":"https://api.statorium.com/media/bearleague/bl17207463292647.webp"},"awayParticipant":{"participantID":2806,"score":1,"participantName":"VfB Stuttgart II","teamShortName":"STU II","teamMiddleName":"Stuttgart II","logo":"https://api.statorium.com/media/bearleague/bl17207470461799.webp"},"playerEvents":[]},{"matchID":90615,"matchDate":"2025-03-30","matchTime":"17:30","minutes_played":71,"lineUP":"1","homeParticipant":{"participantID":2806,"score":2,"participantName":"VfB Stuttgart II","teamShortName":"STU II","teamMiddleName":"Stuttgart II","logo":"https://api.statorium.com/media/bearleague/bl17207470461799.webp"},"awayParticipant":{"participantID":916,"score":1,"participantName":"SV Sandhausen","teamShortName":"SVS","teamMiddleName":"Sandhausen","logo":"https://api.statorium.com/media/bearleague/bl16154605831691.webp"},"playerEvents":[{"eventID":5,"eventName":"Yellow card","minutes":"25"}]},{"matchID":90605,"matchDate":"2025-03-14","matchTime":"18:00","minutes_played":"90","lineUP":"1","homeParticipant":{"participantID":1289,"score":0,"participantName":"1. FC Saarbrücken","teamShortName":"FCS","teamMiddleName":"Saarbrücken","logo":"https://api.statorium.com/media/bearleague/bl16558179732987.webp"},"awayParticipant":{"participantID":2806,"score":2,"participantName":"VfB Stuttgart II","teamShortName":"STU II","teamMiddleName":"Stuttgart II","logo":"https://api.statorium.com/media/bearleague/bl17207470461799.webp"},"playerEvents":[{"eventID":1,"eventName":"Goal","minutes":"35"}]},{"matchID":90595,"matchDate":"2025-03-11","matchTime":"18:00","minutes_played":87,"lineUP":"1","homeParticipant":{"participantID":2806,"score":1,"participantName":"VfB Stuttgart II","teamShortName":"STU II","teamMiddleName":"Stuttgart II","logo":"https://api.statorium.com/media/bearleague/bl17207470461799.webp"},"awayParticipant":{"participantID":915,"score":2,"participantName":"VfL Osnabrück","teamShortName":"OSN","teamMiddleName":"Osnabrück","logo":"https://api.statorium.com/media/bearleague/bl16886921952722.webp"},"playerEvents":[]},{"matchID":90586,"matchDate":"2025-03-08","matchTime":"13:00","minutes_played":4,"lineUP":"0","homeParticipant":{"participantID":2806,"score":2,"participantName":"VfB Stuttgart II","teamShortName":"STU II","teamMiddleName":"Stuttgart II","logo":"https://api.statorium.com/media/bearleague/bl17207470461799.webp"},"awayParticipant":{"participantID":2807,"score":1,"participantName":"Hannover 96 II","teamShortName":"HAN II","teamMiddleName":"Hannover II","logo":"https://api.statorium.com/media/bearleague/bl1720747268993.webp"},"playerEvents":[]},{"matchID":90515,"matchDate":"2025-01-18","matchTime":"13:00","minutes_played":13,"lineUP":"0","homeParticipant":{"participantID":2806,"score":0,"participantName":"VfB Stuttgart II","teamShortName":"STU II","teamMiddleName":"Stuttgart II","logo":"https://api.statorium.com/media/bearleague/bl17207470461799.webp"},"awayParticipant":{"participantID":973,"score":3,"participantName":"FC Hansa Rostock","teamShortName":"HAN","teamMiddleName":"Hansa Rostock","logo":"https://api.statorium.com/media/bearleague/bl1625144597924.webp"},"playerEvents":[]},{"matchID":90505,"matchDate":"2024-12-21","matchTime":"13:00","minutes_played":24,"lineUP":"0","homeParticipant":{"participantID":1285,"score":2,"participantName":"Rot-Weiss Essen","teamShortName":"RWE","teamMiddleName":"Essen","logo":"https://api.statorium.com/media/bearleague/bl16558166382360.webp"},"awayParticipant":{"participantID":2806,"score":2,"participantName":"VfB Stuttgart II","teamShortName":"STU II","teamMiddleName":"Stuttgart II","logo":"https://api.statorium.com/media/bearleague/bl17207470461799.webp"},"playerEvents":[]},{"matchID":90496,"matchDate":"2024-12-14","matchTime":"13:00","minutes_played":9,"lineUP":"0","homeParticipant":{"participantID":2806,"score":0,"participantName":"VfB Stuttgart II","teamShortName":"STU II","teamMiddleName":"Stuttgart II","logo":"https://api.statorium.com/media/bearleague/bl17207470461799.webp"},"awayParticipant":{"participantID":1283,"score":3,"participantName":"Borussia Dortmund II","teamShortName":"BVB II","teamMiddleName":"Dortmund II","logo":"https://api.statorium.com/media/bearleague/bl17158005282749.webp"},"playerEvents":[]}]}