{"playerID":63684,"firstName":"Shio","lastName":"Fukuda","shortName":"S. Fukuda","fullName":"Shio Fukuda","homeName":"福田 師王","country":{"name":"Japan","id":110},"currentTeam":{"name":null,"id":0},"photo":"","additionalInfo":{"height":"178 cm","weight":"70 kg","position":4,"Fantasy Value":null,"birthdate":"08-04-2004  (22)"},"teams":[],"stat":[{"season_name":"GERMANY: 2. Bundesliga 2025-26","season_id":522,"team_name":"Karlsruher SC","played":16,"career_lineup":2,"career_minutes":425,"career_subsin":14,"career_subsout":1,"1 Point (basketball)":0,"2 Points (basketball)":0,"3 Points (basketball)":0,"Points (basketball)":0,"Goals":3,"Assist":0,"Yellow card":1,"Second yellow":0,"Red card":0,"Own goal":0,"Penalty goal":0,"Missed penalty":0,"Goal":3,"Penalty shootout scored":0,"Penalty shootout missed":0},{"season_name":"GERMANY: Bundesliga 2025-26","season_id":521,"team_name":"Borussia Mönchengladbach","played":0,"career_lineup":0,"career_minutes":0,"career_subsin":0,"career_subsout":0,"1 Point (basketball)":0,"2 Points (basketball)":0,"3 Points (basketball)":0,"Points (basketball)":0,"Goals":0,"Assist":0,"Yellow card":0,"Second yellow":0,"Red card":0,"Own goal":0,"Penalty goal":0,"Missed penalty":0,"Goal":0,"Penalty shootout scored":0,"Penalty shootout missed":0},{"season_name":"GERMANY: Bundesliga 2024-25","season_id":385,"team_name":"Borussia Mönchengladbach","played":6,"career_lineup":0,"career_minutes":54,"career_subsin":6,"career_subsout":0,"1 Point (basketball)":0,"2 Points (basketball)":0,"3 Points (basketball)":0,"Points (basketball)":0,"Goals":1,"Assist":0,"Yellow card":0,"Second yellow":0,"Red card":0,"Own goal":0,"Penalty goal":0,"Missed penalty":0,"Goal":1,"Penalty shootout scored":0,"Penalty shootout missed":0},{"season_name":"GERMANY: Bundesliga 2023-24","season_id":274,"team_name":"Borussia Mönchengladbach","played":5,"career_lineup":0,"career_minutes":31,"career_subsin":5,"career_subsout":0,"1 Point (basketball)":0,"2 Points (basketball)":0,"3 Points (basketball)":0,"Points (basketball)":0,"Goals":0,"Assist":0,"Yellow card":0,"Second yellow":0,"Red card":0,"Own goal":0,"Penalty goal":0,"Missed penalty":0,"Goal":0,"Penalty shootout scored":0,"Penalty shootout missed":0}],"matches":[{"matchID":123993,"matchDate":"2026-04-25","matchTime":"11:00","minutes_played":"90","lineUP":"1","homeParticipant":{"participantID":909,"score":1,"participantName":"Karlsruher SC","teamShortName":"KSC","teamMiddleName":"Karlsruher","logo":"https://api.statorium.com/media/bearleague/bl16154604461197.webp"},"awayParticipant":{"participantID":53,"score":3,"participantName":"Hannover 96","teamShortName":"HAN","teamMiddleName":"Hannover","logo":"https://api.statorium.com/media/bearleague/bl15529070682276.webp"},"playerEvents":[]},{"matchID":123981,"matchDate":"2026-04-17","matchTime":"16:30","minutes_played":27,"lineUP":"0","homeParticipant":{"participantID":1194,"score":3,"participantName":"SpVgg 07 Elversberg","teamShortName":"SVE","teamMiddleName":"SV Elversberg","logo":"https://api.statorium.com/media/bearleague/bl16558168482039.webp"},"awayParticipant":{"participantID":909,"score":0,"participantName":"Karlsruher SC","teamShortName":"KSC","teamMiddleName":"Karlsruher","logo":"https://api.statorium.com/media/bearleague/bl16154604461197.webp"},"playerEvents":[]},{"matchID":123975,"matchDate":"2026-04-10","matchTime":"16:30","minutes_played":13,"lineUP":"0","homeParticipant":{"participantID":909,"score":4,"participantName":"Karlsruher SC","teamShortName":"KSC","teamMiddleName":"Karlsruher","logo":"https://api.statorium.com/media/bearleague/bl16154604461197.webp"},"awayParticipant":{"participantID":596,"score":1,"participantName":"DSC Arminia Bielefeld","teamShortName":"ARM","teamMiddleName":"Arminia Bielefeld","logo":"https://api.statorium.com/media/bearleague/bl15968699821559.webp"},"playerEvents":[{"eventID":1,"eventName":"Goal","minutes":"89"}]},{"matchID":123968,"matchDate":"2026-04-05","matchTime":"11:30","minutes_played":26,"lineUP":"0","homeParticipant":{"participantID":41,"score":1,"participantName":"FC Schalke 04","teamShortName":"S04","teamMiddleName":"Schalke","logo":"https://api.statorium.com/media/bearleague/bl15529087481504.webp"},"awayParticipant":{"participantID":909,"score":0,"participantName":"Karlsruher SC","teamShortName":"KSC","teamMiddleName":"Karlsruher","logo":"https://api.statorium.com/media/bearleague/bl16154604461197.webp"},"playerEvents":[]},{"matchID":123957,"matchDate":"2026-03-20","matchTime":"17:30","minutes_played":8,"lineUP":"0","homeParticipant":{"participantID":909,"score":3,"participantName":"Karlsruher SC","teamShortName":"KSC","teamMiddleName":"Karlsruher","logo":"https://api.statorium.com/media/bearleague/bl16154604461197.webp"},"awayParticipant":{"participantID":908,"score":1,"participantName":"SpVgg Greuther Fürth","teamShortName":"SGF","teamMiddleName":"Greuther Fürth","logo":"https://api.statorium.com/media/bearleague/bl16154604652707.webp"},"playerEvents":[{"eventID":1,"eventName":"Goal","minutes":"90+3"}]},{"matchID":123914,"matchDate":"2026-02-13","matchTime":"17:30","minutes_played":58,"lineUP":"1","homeParticipant":{"participantID":51,"score":5,"participantName":"1. FC Nürnberg","teamShortName":"NUR","teamMiddleName":"Nürnberg","logo":"https://api.statorium.com/media/bearleague/bl1552908575324.webp"},"awayParticipant":{"participantID":909,"score":1,"participantName":"Karlsruher SC","teamShortName":"KSC","teamMiddleName":"Karlsruher","logo":"https://api.statorium.com/media/bearleague/bl16154604461197.webp"},"playerEvents":[]},{"matchID":123903,"matchDate":"2026-02-08","matchTime":"12:30","minutes_played":21,"lineUP":"0","homeParticipant":{"participantID":909,"score":1,"participantName":"Karlsruher SC","teamShortName":"KSC","teamMiddleName":"Karlsruher","logo":"https://api.statorium.com/media/bearleague/bl16154604461197.webp"},"awayParticipant":{"participantID":52,"score":1,"participantName":"Fortuna Düsseldorf","teamShortName":"DU","teamMiddleName":"Düsseldorf","logo":"https://api.statorium.com/media/bearleague/bl1552906966622.webp"},"playerEvents":[]},{"matchID":123890,"matchDate":"2026-01-31","matchTime":"12:00","minutes_played":28,"lineUP":"0","homeParticipant":{"participantID":914,"score":1,"participantName":"Eintracht Braunschweig","teamShortName":"EBS","teamMiddleName":"Braunschweig","logo":"https://api.statorium.com/media/bearleague/bl16154603512818.webp"},"awayParticipant":{"participantID":909,"score":0,"participantName":"Karlsruher SC","teamShortName":"KSC","teamMiddleName":"Karlsruher","logo":"https://api.statorium.com/media/bearleague/bl16154604461197.webp"},"playerEvents":[{"eventID":5,"eventName":"Yellow card","minutes":"84"}]},{"matchID":123862,"matchDate":"2025-12-20","matchTime":"12:00","minutes_played":44,"lineUP":"0","homeParticipant":{"participantID":905,"score":2,"participantName":"VfL Bochum","teamShortName":"BOC","teamMiddleName":"Bochum","logo":"https://api.statorium.com/media/bearleague/bl17162964901569.webp"},"awayParticipant":{"participantID":909,"score":2,"participantName":"Karlsruher SC","teamShortName":"KSC","teamMiddleName":"Karlsruher","logo":"https://api.statorium.com/media/bearleague/bl16154604461197.webp"},"playerEvents":[{"eventID":1,"eventName":"Goal","minutes":"86"}]},{"matchID":123839,"matchDate":"2025-11-28","matchTime":"17:30","minutes_played":16,"lineUP":"0","homeParticipant":{"participantID":53,"score":3,"participantName":"Hannover 96","teamShortName":"HAN","teamMiddleName":"Hannover","logo":"https://api.statorium.com/media/bearleague/bl15529070682276.webp"},"awayParticipant":{"participantID":909,"score":0,"participantName":"Karlsruher SC","teamShortName":"KSC","teamMiddleName":"Karlsruher","logo":"https://api.statorium.com/media/bearleague/bl16154604461197.webp"},"playerEvents":[]},{"matchID":123831,"matchDate":"2025-11-23","matchTime":"12:30","minutes_played":10,"lineUP":"0","homeParticipant":{"participantID":909,"score":2,"participantName":"Karlsruher SC","teamShortName":"KSC","teamMiddleName":"Karlsruher","logo":"https://api.statorium.com/media/bearleague/bl16154604461197.webp"},"awayParticipant":{"participantID":1194,"score":3,"participantName":"SpVgg 07 Elversberg","teamShortName":"SVE","teamMiddleName":"SV Elversberg","logo":"https://api.statorium.com/media/bearleague/bl16558168482039.webp"},"playerEvents":[]},{"matchID":123813,"matchDate":"2025-11-01","matchTime":"12:00","minutes_played":17,"lineUP":"0","homeParticipant":{"participantID":909,"score":2,"participantName":"Karlsruher SC","teamShortName":"KSC","teamMiddleName":"Karlsruher","logo":"https://api.statorium.com/media/bearleague/bl16154604461197.webp"},"awayParticipant":{"participantID":41,"score":1,"participantName":"FC Schalke 04","teamShortName":"S04","teamMiddleName":"Schalke","logo":"https://api.statorium.com/media/bearleague/bl15529087481504.webp"},"playerEvents":[]},{"matchID":123776,"matchDate":"2025-09-27","matchTime":"11:00","minutes_played":20,"lineUP":"0","homeParticipant":{"participantID":909,"score":1,"participantName":"Karlsruher SC","teamShortName":"KSC","teamMiddleName":"Karlsruher","logo":"https://api.statorium.com/media/bearleague/bl16154604461197.webp"},"awayParticipant":{"participantID":1196,"score":0,"participantName":"1. FC Magdeburg","teamShortName":"FCM","teamMiddleName":"Magdeburg","logo":"https://api.statorium.com/media/bearleague/bl1720184713268.webp"},"playerEvents":[]},{"matchID":123767,"matchDate":"2025-09-21","matchTime":"11:30","minutes_played":21,"lineUP":"0","homeParticipant":{"participantID":906,"score":3,"participantName":"Holstein Kiel","teamShortName":"HOL","teamMiddleName":"Holstein Kiel","logo":"https://api.statorium.com/media/bearleague/bl16558251361774.webp"},"awayParticipant":{"participantID":909,"score":0,"participantName":"Karlsruher SC","teamShortName":"KSC","teamMiddleName":"Karlsruher","logo":"https://api.statorium.com/media/bearleague/bl16154604461197.webp"},"playerEvents":[]},{"matchID":123759,"matchDate":"2025-09-13","matchTime":"11:00","minutes_played":17,"lineUP":"0","homeParticipant":{"participantID":909,"score":2,"participantName":"Karlsruher SC","teamShortName":"KSC","teamMiddleName":"Karlsruher","logo":"https://api.statorium.com/media/bearleague/bl16154604461197.webp"},"awayParticipant":{"participantID":51,"score":1,"participantName":"1. FC Nürnberg","teamShortName":"NUR","teamMiddleName":"Nürnberg","logo":"https://api.statorium.com/media/bearleague/bl1552908575324.webp"},"playerEvents":[]},{"matchID":123747,"matchDate":"2025-08-30","matchTime":"18:30","minutes_played":9,"lineUP":"0","homeParticipant":{"participantID":52,"score":0,"participantName":"Fortuna Düsseldorf","teamShortName":"DU","teamMiddleName":"Düsseldorf","logo":"https://api.statorium.com/media/bearleague/bl1552906966622.webp"},"awayParticipant":{"participantID":909,"score":0,"participantName":"Karlsruher SC","teamShortName":"KSC","teamMiddleName":"Karlsruher","logo":"https://api.statorium.com/media/bearleague/bl16154604461197.webp"},"playerEvents":[]},{"matchID":86661,"matchDate":"2025-05-17","matchTime":"13:30","minutes_played":8,"lineUP":"0","homeParticipant":{"participantID":49,"score":0,"participantName":"Borussia Mönchengladbach","teamShortName":"BMG","teamMiddleName":"Borussia M'gladbach","logo":"https://api.statorium.com/media/bearleague/bl17162968492930.webp"},"awayParticipant":{"participantID":48,"score":1,"participantName":"VfL Wolfsburg","teamShortName":"WOB","teamMiddleName":"Wolfsburg","logo":"https://api.statorium.com/media/bearleague/bl1716296213736.webp"},"playerEvents":[]},{"matchID":86625,"matchDate":"2025-04-20","matchTime":"15:30","minutes_played":7,"lineUP":"0","homeParticipant":{"participantID":42,"score":3,"participantName":"Borussia Dortmund","teamShortName":"BVB","teamMiddleName":"Dortmund","logo":"https://api.statorium.com/media/bearleague/bl17567958801272.png"},"awayParticipant":{"participantID":49,"score":2,"participantName":"Borussia Mönchengladbach","teamShortName":"BMG","teamMiddleName":"Borussia M'gladbach","logo":"https://api.statorium.com/media/bearleague/bl17162968492930.webp"},"playerEvents":[]},{"matchID":86579,"matchDate":"2025-03-07","matchTime":"19:30","minutes_played":16,"lineUP":"0","homeParticipant":{"participantID":49,"score":1,"participantName":"Borussia Mönchengladbach","teamShortName":"BMG","teamMiddleName":"Borussia M'gladbach","logo":"https://api.statorium.com/media/bearleague/bl17162968492930.webp"},"awayParticipant":{"participantID":50,"score":3,"participantName":"1. FSV Mainz 05","teamShortName":"MAI","teamMiddleName":"Mainz 05","logo":"https://api.statorium.com/media/bearleague/bl17162968832533.webp"},"playerEvents":[]},{"matchID":86516,"matchDate":"2025-01-18","matchTime":"17:30","minutes_played":3,"lineUP":"0","homeParticipant":{"participantID":57,"score":3,"participantName":"Bayer 04 Leverkusen","teamShortName":"B04","teamMiddleName":"Leverkusen","logo":"https://api.statorium.com/media/bearleague/bl1716291195914.webp"},"awayParticipant":{"participantID":49,"score":1,"participantName":"Borussia Mönchengladbach","teamShortName":"BMG","teamMiddleName":"Borussia M'gladbach","logo":"https://api.statorium.com/media/bearleague/bl17162968492930.webp"},"playerEvents":[]},{"matchID":86515,"matchDate":"2025-01-14","matchTime":"19:30","minutes_played":20,"lineUP":"0","homeParticipant":{"participantID":48,"score":5,"participantName":"VfL Wolfsburg","teamShortName":"WOB","teamMiddleName":"Wolfsburg","logo":"https://api.statorium.com/media/bearleague/bl1716296213736.webp"},"awayParticipant":{"participantID":49,"score":1,"participantName":"Borussia Mönchengladbach","teamShortName":"BMG","teamMiddleName":"Borussia M'gladbach","logo":"https://api.statorium.com/media/bearleague/bl17162968492930.webp"},"playerEvents":[{"eventID":1,"eventName":"Goal","minutes":"89"}]},{"matchID":63224,"matchDate":"2024-05-18","matchTime":"13:30","minutes_played":10,"lineUP":"0","homeParticipant":{"participantID":56,"score":4,"participantName":"VfB Stuttgart","teamShortName":"STU","teamMiddleName":"Stuttgart","logo":"https://api.statorium.com/media/bearleague/bl1716295960587.webp"},"awayParticipant":{"participantID":49,"score":0,"participantName":"Borussia Mönchengladbach","teamShortName":"BMG","teamMiddleName":"Borussia M'gladbach","logo":"https://api.statorium.com/media/bearleague/bl17162968492930.webp"},"playerEvents":[]},{"matchID":63118,"matchDate":"2024-02-17","matchTime":"17:30","minutes_played":5,"lineUP":"0","homeParticipant":{"participantID":45,"score":2,"participantName":"RB Leipzig","teamShortName":"RBL","teamMiddleName":"Leipzig","logo":"https://api.statorium.com/media/bearleague/bl17162960002046.webp"},"awayParticipant":{"participantID":49,"score":0,"participantName":"Borussia Mönchengladbach","teamShortName":"BMG","teamMiddleName":"Borussia M'gladbach","logo":"https://api.statorium.com/media/bearleague/bl17162968492930.webp"},"playerEvents":[]},{"matchID":63093,"matchDate":"2024-02-03","matchTime":"14:30","minutes_played":5,"lineUP":"0","homeParticipant":{"participantID":47,"score":3,"participantName":"FC Bayern München","teamShortName":"BAY","teamMiddleName":"Bayern","logo":"https://api.statorium.com/media/bearleague/bl17295151342331.webp"},"awayParticipant":{"participantID":49,"score":1,"participantName":"Borussia Mönchengladbach","teamShortName":"BMG","teamMiddleName":"Borussia M'gladbach","logo":"https://api.statorium.com/media/bearleague/bl17162968492930.webp"},"playerEvents":[]},{"matchID":63085,"matchDate":"2024-01-27","matchTime":"17:30","minutes_played":11,"lineUP":"0","homeParticipant":{"participantID":57,"score":0,"participantName":"Bayer 04 Leverkusen","teamShortName":"B04","teamMiddleName":"Leverkusen","logo":"https://api.statorium.com/media/bearleague/bl1716291195914.webp"},"awayParticipant":{"participantID":49,"score":0,"participantName":"Borussia Mönchengladbach","teamShortName":"BMG","teamMiddleName":"Borussia M'gladbach","logo":"https://api.statorium.com/media/bearleague/bl17162968492930.webp"},"playerEvents":[]}]}